kubeobject/__init__.py
kubeobject/customobject.py
kubeobject/exceptions.py
kubeobject/kubeobject.py
tests/__init__.py
tests/test_custom_object.py
tests/test_generate_random_name.py
tests/test_kubeobject.py
kubeobject-0.2.1.dist-info/LICENSE
kubeobject-0.2.1.dist-info/METADATA
kubeobject-0.2.1.dist-info/WHEEL
kubeobject-0.2.1.dist-info/top_level.txt
kubeobject-0.2.1.dist-info/RECORD
