Metadata-Version: 2.1
Name: kubeobject
Version: 0.2.1
Summary: Easily Manage Kubernetes Objects.
Home-page: https://github.com/mongodb/kubeobject
Author: Rodrigo Valin
Author-email: rodrigo.valin@mongodb.com
License: UNKNOWN
Platform: UNKNOWN
License-File: LICENSE
Requires-Dist: kubernetes (==17.17.0)
Requires-Dist: PyYAML (==5.4.1)
Requires-Dist: python-box (==5.3.0)
